air_convert/__init__.py
air_convert/__main__.py
air_convert/air_convert.py
air_convert/cli.py
air_convert-0.3.0.dist-info/licenses/LICENSE
air_convert-0.3.0.dist-info/METADATA
air_convert-0.3.0.dist-info/WHEEL
air_convert-0.3.0.dist-info/entry_points.txt
air_convert-0.3.0.dist-info/top_level.txt
air_convert-0.3.0.dist-info/RECORD
